setup.py
salure_helpers/dynamics/__init__.py
salure_helpers/dynamics/dynamics.py
salure_helpers_dynamics.egg-info/PKG-INFO
salure_helpers_dynamics.egg-info/SOURCES.txt
salure_helpers_dynamics.egg-info/dependency_links.txt
salure_helpers_dynamics.egg-info/not-zip-safe
salure_helpers_dynamics.egg-info/requires.txt
salure_helpers_dynamics.egg-info/top_level.txt