Metadata-Version: 1.0
Name: salure-helpers-dynamics
Version: 0.0.2
Summary: Datev wrapper from Dynamics365
Home-page: UNKNOWN
Author: D&A Salure
Author-email: support@salureconnnect.com
License: Salure License
Platform: UNKNOWN
